README.md
setup.cfg
setup.py
repo_link/__init__.py
repo_link/repo_link.py
repo_link.egg-info/PKG-INFO
repo_link.egg-info/SOURCES.txt
repo_link.egg-info/dependency_links.txt
repo_link.egg-info/entry_points.txt
repo_link.egg-info/requires.txt
repo_link.egg-info/top_level.txt