Metadata-Version: 2.1
Name: repo-link
Version: 0.1
Summary: Open github links in your editor
Home-page: https://github.com/Tadaboody/repo_link
Author: Tomer Keren
Author-email: tomer.keren.dev@gmail.com
License: MIT
Platform: UNKNOWN
Classifier: Development Status :: 3 - Alpha
Classifier: Programming Language :: Python :: 3
Classifier: Programming Language :: Python :: 3.7
Classifier: Environment :: Console
Classifier: Operating System :: OS Independent
Classifier: License :: OSI Approved :: MIT License
